setup.py
raet/__init__.py
raet/__metadata__.py
raet/abiding.py
raet/encoding.py
raet/keeping.py
raet/lotting.py
raet/nacling.py
raet/raeting.py
raet/stacking.py
raet/flo/__init__.py
raet/flo/behaving.py
raet/flo/plan/lanetest.flo
raet/flo/plan/managetest.flo
raet/flo/plan/master.flo
raet/flo/plan/masterminion1.flo
raet/flo/plan/masterminion2.flo
raet/flo/plan/minion.flo
raet/flo/plan/minion1.flo
raet/flo/plan/minion2.flo
raet/flo/plan/roadtest.flo
raet/flo/plan/routetest.flo
raet/flo/test/__init__.py
raet/flo/test/test_behaving.py
raet/lane/__init__.py
raet/lane/paging.py
raet/lane/stacking.py
raet/lane/yarding.py
raet/lane/test/__init__.py
raet/lane/test/test_paging.py
raet/lane/test/test_stacking.py
raet/road/__init__.py
raet/road/estating.py
raet/road/keeping.py
raet/road/packeting.py
raet/road/stacking.py
raet/road/transacting.py
raet/road/test/__init__.py
raet/road/test/test_joining.py
raet/road/test/test_keeping.py
raet/road/test/test_messaging.py
raet/road/test/test_packeting.py
raet/road/test/test_presenting.py
raet/road/test/test_stacking.py
raet/test/__init__.py
raet/test/test_nacling.py
raet/test/test_template.py
raetp.egg-info/PKG-INFO
raetp.egg-info/SOURCES.txt
raetp.egg-info/dependency_links.txt
raetp.egg-info/requires.txt
raetp.egg-info/top_level.txt
scripts/raetflo
systest/__init__.py
systest/lib/__init__.py
systest/lib/data.py
systest/lib/mp_helper.py
systest/lib/netem.py