Metadata-Version: 1.1
Name: raetp
Version: 0.6.3
Summary: Reliable Asynchronous Event Transport protocol
Home-page: https://github.com/RaetProtocol/raet.git
Author: Samuel M. Smith
Author-email: info@ioflo.com
License: Apache2
Download-URL: https://github.com/RaetProtocol/raet/archive/master.zip
Keywords: UDP UXD Communications CurveCP Elliptic Curve CryptoReliable Asynchronous Event Transport Protocol
Platform: UNKNOWN
